[
  {
    "name": "",
    "header": "",
    "footer": "",
    "id": null
  },
  {
    "name": "nameg 6H",
    "header": "headerLcfm",
    "footer": "footergLSq0L4",
    "id": null
  },
  {
    "name": "name  aKc",
    "header": "header9",
    "footer": "footergv",
    "id": null
  },
  {
    "name": "name hB ",
    "header": "headerxaW3",
    "footer": "footerO UkXQB rZ hS 8is",
    "id": null
  },
  {
    "name": "nameGla",
    "header": "headerufS",
    "footer": "footer",
    "id": null
  },
  {
    "name": "namezP 3c k3",
    "header": "headerJ",
    "footer": "footerBv5BRXMB g1OeprRL6",
    "id": null
  }
]